depthcharge/__init__.py
depthcharge/masses.py
depthcharge/similarity.py
depthcharge/utils.py
depthcharge/version.py
depthcharge/components/__init__.py
depthcharge/components/encoders.py
depthcharge/components/feedforward.py
depthcharge/components/mixins.py
depthcharge/components/transformers.py
depthcharge/data/__init__.py
depthcharge/data/datasets.py
depthcharge/data/hdf5.py
depthcharge/data/parsers.py
depthcharge/data/preprocessing.py
lslcharge-0.1.11.dist-info/LICENSE
lslcharge-0.1.11.dist-info/METADATA
lslcharge-0.1.11.dist-info/WHEEL
lslcharge-0.1.11.dist-info/entry_points.txt
lslcharge-0.1.11.dist-info/top_level.txt
lslcharge-0.1.11.dist-info/RECORD
