Metadata-Version: 2.1
Name: lslcharge
Version: 0.1.11
Summary: A deep learning toolkit for proteomics, equipped with a few tools for network recycling.
Home-page: https://github.com/Leslie-Jiang-Hamster
Author: William E. Fondrie & Leslie Jiang
Author-email: fondriew@gmail.com & Leslie_Jiang@proton.me
License: Apache 2.0
Project-URL: Documentation, https://depthcharge.readthedocs.io
Project-URL: Bug Tracker, https://github.com/wfondrie/depthcharge/issues
Project-URL: Discussion Board, https://github.com/wfondrie/depthcharge/discussions
Classifier: Programming Language :: Python :: 3
Classifier: License :: OSI Approved :: Apache Software License
Classifier: Operating System :: OS Independent
Classifier: Topic :: Scientific/Engineering :: Bio-Informatics
Requires-Python: >=3.8
License-File: LICENSE
Requires-Dist: torch >=1.11.0
Requires-Dist: pyteomics >=4.4.2
Requires-Dist: numpy >=1.18.1
Requires-Dist: pandas >=1.0.3
Requires-Dist: numba >=0.48.0
Requires-Dist: lxml >=4.9.1
Requires-Dist: h5py >=3.7.0
Requires-Dist: einops >=0.4.1
Requires-Dist: tqdm >=4.65.0
Provides-Extra: dev
Requires-Dist: pre-commit >=2.7.1 ; extra == 'dev'
Requires-Dist: black >=19.10b0 ; extra == 'dev'
Provides-Extra: docs
Requires-Dist: mkdocs ; extra == 'docs'
Requires-Dist: mkdocs-material ; extra == 'docs'
Requires-Dist: mkdocstrings ; extra == 'docs'
Requires-Dist: mkdocstrings-python ; extra == 'docs'
Provides-Extra: tensorboard
Requires-Dist: tesnsorboard >=2.11.0 ; extra == 'tensorboard'
